saultcollege_csd110_25f_linewise/__init__.py
saultcollege_csd110_25f_linewise/__main__.py
saultcollege_csd110_25f_linewise/cli.py
saultcollege_csd110_25f_linewise-0.1.3.dist-info/entry_points.txt
saultcollege_csd110_25f_linewise-0.1.3.dist-info/METADATA
saultcollege_csd110_25f_linewise-0.1.3.dist-info/WHEEL
saultcollege_csd110_25f_linewise-0.1.3.dist-info/RECORD
