Metadata-Version: 2.4
Name: saultcollege-csd110-25f-linewise
Version: 0.1.3
Summary: A command-line tool for counting lines, words, and characters.
Author: Vinicius Silva
Author-email: 128252447+vini-porto@users.noreply.github.com
Requires-Python: >=3.13
Classifier: Programming Language :: Python :: 3
Classifier: Programming Language :: Python :: 3.13
Classifier: Programming Language :: Python :: 3.14
